{"nodes": [{"id": "readme_flowforge", "label": "FlowForge Platform", "file_type": "concept", "source_file": "README.md", "source_location": null, "source_url": null, "captured_at": null, "author": null, "contributor": null}, {"id": "readme_dag_workflow_automation", "label": "DAG-based Workflow Automation", "file_type": "rationale", "source_file": "README.md", "source_location": null, "source_url": null, "captured_at": null, "author": null, "contributor": null}, {"id": "readme_multi_tenancy", "label": "Multi-tenancy", "file_type": "rationale", "source_file": "README.md", "source_location": null, "source_url": null, "captured_at": null, "author": null, "contributor": null}, {"id": "readme_real_time_monitoring", "label": "Real-time Monitoring", "file_type": "rationale", "source_file": "README.md", "source_location": null, "source_url": null, "captured_at": null, "author": null, "contributor": null}, {"id": "readme_http_call_node_type", "label": "HTTP_CALL Node Type", "file_type": "concept", "source_file": "README.md", "source_location": null, "source_url": null, "captured_at": null, "author": null, "contributor": null}, {"id": "readme_delay_node_type", "label": "DELAY Node Type", "file_type": "concept", "source_file": "README.md", "source_location": null, "source_url": null, "captured_at": null, "author": null, "contributor": null}, {"id": "readme_data_transform_node_type", "label": "DATA_TRANSFORM Node Type", "file_type": "concept", "source_file": "README.md", "source_location": null, "source_url": null, "captured_at": null, "author": null, "contributor": null}, {"id": "readme_conditional_branch_node_type", "label": "CONDITIONAL_BRANCH Node Type", "file_type": "concept", "source_file": "README.md", "source_location": null, "source_url": null, "captured_at": null, "author": null, "contributor": null}], "edges": [{"source": "readme_flowforge", "target": "readme_dag_workflow_automation", "relation": "conceptually_related_to", "confidence": "INFERRED", "confidence_score": 0.95, "source_file": "README.md", "source_location": null, "weight": 1.0}, {"source": "readme_flowforge", "target": "readme_multi_tenancy", "relation": "conceptually_related_to", "confidence": "INFERRED", "confidence_score": 0.85, "source_file": "README.md", "source_location": null, "weight": 1.0}, {"source": "readme_flowforge", "target": "readme_real_time_monitoring", "relation": "conceptually_related_to", "confidence": "INFERRED", "confidence_score": 0.85, "source_file": "README.md", "source_location": null, "weight": 1.0}], "hyperedges": []}