{"C:\\Users\\mattar\\Private\\code\\project\\flow-forge\\.agents\\skills\\react-router\\SKILL.md":{"size":6104,"mtime_ns":1784161475218966700,"word_count":588,"hash":"ba177217bb54d968a0eae4a2d738b70f8e805136f51431bfaddf9f99f594fcb5"},"C:\\Users\\mattar\\Private\\code\\project\\flow-forge\\.agents\\skills\\react-router\\references\\data-mode.md":{"size":4797,"mtime_ns":1784161475138985900,"word_count":588,"hash":"723737535446a898f93141b990a0cdb1de0844c98c26e2bf8afec3e2634ef4f3"},"C:\\Users\\mattar\\Private\\code\\project\\flow-forge\\.agents\\skills\\react-router\\references\\declarative-mode.md":{"size":3284,"mtime_ns":1784161475169915500,"word_count":422,"hash":"047de0644af19a07b05ac63211e475399703f4fd7304c4660a1f26621de54ee4"},"C:\\Users\\mattar\\Private\\code\\project\\flow-forge\\.agents\\skills\\react-router\\references\\framework-mode.md":{"size":7271,"mtime_ns":1784161475169915500,"word_count":807,"hash":"d2eb61cb80b1e9d974955ae8a36ba6f5428fc09d262f58f4a085b2fe61e27a19"},"C:\\Users\\mattar\\Private\\code\\project\\flow-forge\\.agents\\skills\\react-router\\references\\rsc.md":{"size":3447,"mtime_ns":1784161475188647400,"word_count":481,"hash":"1ade30150b77579972af425243a055e7d7d091601481acfd1b62b6995e7209ae"},"C:\\Users\\mattar\\Private\\code\\project\\flow-forge\\.opencode\\opencode.json":{"size":109,"mtime_ns":1784171509036512300,"word_count":8,"hash":"87f9eaf03548caf8cf2fbb77a65f5d020b97ca2eaa85948eeb2f2576c1b67de8"},"C:\\Users\\mattar\\Private\\code\\project\\flow-forge\\.opencode\\plugins\\graphify.js":{"size":1432,"mtime_ns":1784171466392769400,"word_count":197},"C:\\Users\\mattar\\Private\\code\\project\\flow-forge\\AGENTS.md":{"size":1141,"mtime_ns":1784171466388773400,"word_count":165,"hash":"60a156b83858ebc773b018efc4cb356646f2dfdf762a3eaae9446a6dfcf4ec20"},"C:\\Users\\mattar\\Private\\code\\project\\flow-forge\\compose.yml":{"size":478,"mtime_ns":1784168717680204600,"word_count":33,"hash":"2b248950d76a8f84887570bf7a04089e8679bf769fec4c1effeb70d923972db2"},"C:\\Users\\mattar\\Private\\code\\project\\flow-forge\\docs\\architecture-decision.md":{"size":12569,"mtime_ns":1784174430312793300,"word_count":1770},"C:\\Users\\mattar\\Private\\code\\project\\flow-forge\\docs\\business-logic.md":{"size":10485,"mtime_ns":1784169698804154300,"word_count":1485,"hash":"942b882d53b831bd5d00df24e3d0989ac4e129f5d184463842df9c162b8ddfab"},"C:\\Users\\mattar\\Private\\code\\project\\flow-forge\\docs\\database-schema.md":{"size":7049,"mtime_ns":1784169633378504600,"word_count":872,"hash":"df018ba604a11dea20684cbff505739fedcff161685e81598814c31e281e7057"},"C:\\Users\\mattar\\Private\\code\\project\\flow-forge\\package.json":{"size":260,"mtime_ns":1784154765338803200,"word_count":30,"hash":"d11a4b96de95a0ecadaea7914c5cd2eae777f6ab67ab9924492da3afe2815e08"},"C:\\Users\\mattar\\Private\\code\\project\\flow-forge\\pnpm-workspace.yaml":{"size":34,"mtime_ns":1784155264930816900,"word_count":5,"hash":"5ebc9044a04ce9a258d7cc387c989205ed1c7ea2d91fb7dad1b13deae2477f47"},"C:\\Users\\mattar\\Private\\code\\project\\flow-forge\\src\\api\\README.md":{"size":5134,"mtime_ns":1784155455595293200,"word_count":472,"hash":"c2e60428e3855039310b6addc591e72e25aa56ee22df49c0cc63b16bc34c05c5"},"C:\\Users\\mattar\\Private\\code\\project\\flow-forge\\src\\api\\eslint.config.mjs":{"size":869,"mtime_ns":1784155455578360300,"word_count":59},"C:\\Users\\mattar\\Private\\code\\project\\flow-forge\\src\\api\\nest-cli.json":{"size":179,"mtime_ns":1784155455578360300,"word_count":13,"hash":"76ee94d3f1cf929dd71e79b25f25ea4ec05ba940e824b4352c7fd3bb2f183c0a"},"C:\\Users\\mattar\\Private\\code\\project\\flow-forge\\src\\api\\package.json":{"size":2062,"mtime_ns":1784174604162011100,"word_count":159,"hash":"6d79e78e414c2376064b405d5bb34a8f5c0a99369342387c1da9e2fe2c8f6735"},"C:\\Users\\mattar\\Private\\code\\project\\flow-forge\\src\\api\\src\\app.controller.spec.ts":{"size":617,"mtime_ns":1784156717231280300,"word_count":61},"C:\\Users\\mattar\\Private\\code\\project\\flow-forge\\src\\api\\src\\app.controller.ts":{"size":274,"mtime_ns":1784156836066522800,"word_count":31},"C:\\Users\\mattar\\Private\\code\\project\\flow-forge\\src\\api\\src\\app.module.ts":{"size":473,"mtime_ns":1784176070661936500,"word_count":50},"C:\\Users\\mattar\\Private\\code\\project\\flow-forge\\src\\api\\src\\app.service.ts":{"size":142,"mtime_ns":1784156834271810200,"word_count":19},"C:\\Users\\mattar\\Private\\code\\project\\flow-forge\\src\\api\\src\\main.ts":{"size":228,"mtime_ns":1784156832967832500,"word_count":27},"C:\\Users\\mattar\\Private\\code\\project\\flow-forge\\src\\api\\test\\app.e2e-spec.ts":{"size":662,"mtime_ns":1784176217032288700,"word_count":69},"C:\\Users\\mattar\\Private\\code\\project\\flow-forge\\src\\api\\test\\jest-e2e.json":{"size":192,"mtime_ns":1784155455645436900,"word_count":17,"hash":"885955b6845077c3d20a9992fca85acd5df85a6edd5eb1d7186688cf10649655"},"C:\\Users\\mattar\\Private\\code\\project\\flow-forge\\src\\api\\tsconfig.build.json":{"size":101,"mtime_ns":1784155455595293200,"word_count":9,"hash":"1522c288e2e3d47502052766ded6ba82a9d776c3de2f916552d733ae1c04bde8"},"C:\\Users\\mattar\\Private\\code\\project\\flow-forge\\src\\api\\tsconfig.json":{"size":765,"mtime_ns":1784175991449933200,"word_count":55,"hash":"656dab64e8fd03a0c13305e3fdd83596671ce50d11b8c1f32ebd83d294a74a5e"},"C:\\Users\\mattar\\Private\\code\\project\\flow-forge\\src\\web\\README.md":{"size":1839,"mtime_ns":1781728720000000000,"word_count":245,"hash":"0417c2823513b75c957f4b755a708baa8fcda64ed7455cecb45ce4edca3f44d3"},"C:\\Users\\mattar\\Private\\code\\project\\flow-forge\\src\\web\\app\\root.tsx":{"size":1787,"mtime_ns":1781728720000000000,"word_count":188},"C:\\Users\\mattar\\Private\\code\\project\\flow-forge\\src\\web\\app\\routes.ts":{"size":134,"mtime_ns":1781728720000000000,"word_count":13},"C:\\Users\\mattar\\Private\\code\\project\\flow-forge\\src\\web\\app\\routes\\home.tsx":{"size":315,"mtime_ns":1781728720000000000,"word_count":47},"C:\\Users\\mattar\\Private\\code\\project\\flow-forge\\src\\web\\app\\welcome\\logo-dark.svg":{"size":6098,"mtime_ns":1781728720000000000,"word_count":543,"hash":"4a8c2b8b8d3d4f9413b4a794514c71196af8e7724a7652668182ef376b5c18cb"},"C:\\Users\\mattar\\Private\\code\\project\\flow-forge\\src\\web\\app\\welcome\\logo-light.svg":{"size":6129,"mtime_ns":1781728720000000000,"word_count":543,"hash":"14a8d5fd66c2cc0ba0fc1df38d70fb78971823d3d9eab292c52adc7da03ca710"},"C:\\Users\\mattar\\Private\\code\\project\\flow-forge\\src\\web\\app\\welcome\\welcome.tsx":{"size":4190,"mtime_ns":1784162130330041900,"word_count":338},"C:\\Users\\mattar\\Private\\code\\project\\flow-forge\\src\\web\\package.json":{"size":718,"mtime_ns":1784161491174915700,"word_count":59,"hash":"c176385d27681ac980b6d0bd6957050e9b69856e71421df307b723db19053705"},"C:\\Users\\mattar\\Private\\code\\project\\flow-forge\\src\\web\\react-router.config.ts":{"size":205,"mtime_ns":1781728720000000000,"word_count":31},"C:\\Users\\mattar\\Private\\code\\project\\flow-forge\\src\\web\\tsconfig.json":{"size":585,"mtime_ns":1781728720000000000,"word_count":47,"hash":"f9f44fb2d1e58dbe31ba52b08204c1c82a354709cd235119a48cd6f3c5fbef58"},"C:\\Users\\mattar\\Private\\code\\project\\flow-forge\\src\\web\\vite.config.ts":{"size":257,"mtime_ns":1781728720000000000,"word_count":28},"C:\\Users\\mattar\\Private\\code\\project\\flow-forge\\src\\worker\\README.md":{"size":5134,"mtime_ns":1784166568180186600,"word_count":472,"hash":"f6b6210f7839c88182da11b863783d3680740e970f4b9ee0e94e199fd5b19c16"},"C:\\Users\\mattar\\Private\\code\\project\\flow-forge\\src\\worker\\eslint.config.mjs":{"size":869,"mtime_ns":1784166568170070400,"word_count":59},"C:\\Users\\mattar\\Private\\code\\project\\flow-forge\\src\\worker\\nest-cli.json":{"size":179,"mtime_ns":1784166568178982200,"word_count":13,"hash":"96939db76c475c54697fe2b57a2a0b6b8e76e6a050e7a41babcae03cf0cbd5e7"},"C:\\Users\\mattar\\Private\\code\\project\\flow-forge\\src\\worker\\package.json":{"size":2048,"mtime_ns":1784166568180186600,"word_count":153,"hash":"602ae0948dea4e2dcccea2331efbffd1c8548c67e18419972fc800cbcdb4876d"},"C:\\Users\\mattar\\Private\\code\\project\\flow-forge\\src\\worker\\src\\app.controller.spec.ts":{"size":617,"mtime_ns":1784166726685689400,"word_count":61},"C:\\Users\\mattar\\Private\\code\\project\\flow-forge\\src\\worker\\src\\app.controller.ts":{"size":274,"mtime_ns":1784166739975491300,"word_count":31},"C:\\Users\\mattar\\Private\\code\\project\\flow-forge\\src\\worker\\src\\app.module.ts":{"size":249,"mtime_ns":1784166746226837900,"word_count":30},"C:\\Users\\mattar\\Private\\code\\project\\flow-forge\\src\\worker\\src\\app.service.ts":{"size":142,"mtime_ns":1784166749956758500,"word_count":19},"C:\\Users\\mattar\\Private\\code\\project\\flow-forge\\src\\worker\\src\\main.ts":{"size":228,"mtime_ns":1784166754321114200,"word_count":27},"C:\\Users\\mattar\\Private\\code\\project\\flow-forge\\src\\worker\\test\\app.e2e-spec.ts":{"size":669,"mtime_ns":1784166847477648100,"word_count":69},"C:\\Users\\mattar\\Private\\code\\project\\flow-forge\\src\\worker\\test\\jest-e2e.json":{"size":192,"mtime_ns":1784166568200064700,"word_count":17,"hash":"a5b40c6e391676cbda8f992702753b30e64fe0e8fd610292fdb19f1da5d6ef03"},"C:\\Users\\mattar\\Private\\code\\project\\flow-forge\\src\\worker\\tsconfig.build.json":{"size":101,"mtime_ns":1784166568180186600,"word_count":9,"hash":"0b1dc04267723d027535261d4876414007ab6edbe3a32f6eb965609a80e54996"},"C:\\Users\\mattar\\Private\\code\\project\\flow-forge\\src\\worker\\tsconfig.json":{"size":712,"mtime_ns":1784166718982627200,"word_count":48,"hash":"be4742474320a009386ed27be3f1072a70f4e6d045d23e00b5b5370fdb9aeb70"},"C:\\Users\\mattar\\Private\\code\\project\\flow-forge\\src\\api\\prisma.config.ts":{"size":195,"mtime_ns":1784175361329951400,"word_count":20},"C:\\Users\\mattar\\Private\\code\\project\\flow-forge\\src\\api\\prisma\\migrations\\20260716042302_init\\migration.sql":{"size":9224,"mtime_ns":1784175782895479900,"word_count":780,"hash":"e828681fb048efee0b234fcc1c3f01afd1434cf535fac3a409f98d7ad7d1b2df"},"C:\\Users\\mattar\\Private\\code\\project\\flow-forge\\src\\api\\src\\shared\\providers\\prisma\\prisma.module.ts":{"size":210,"mtime_ns":1784174697436700600,"word_count":24},"C:\\Users\\mattar\\Private\\code\\project\\flow-forge\\src\\api\\src\\shared\\providers\\prisma\\prisma.service.ts":{"size":350,"mtime_ns":1784174697437700300,"word_count":37}}